tostring/__init__.py
tostring-0.1.0.dist-info/LICENSE
tostring-0.1.0.dist-info/METADATA
tostring-0.1.0.dist-info/WHEEL
tostring-0.1.0.dist-info/top_level.txt
tostring-0.1.0.dist-info/RECORD
